{
  "checks": [
    {
      "timestamp": "2026-02-18T05:13:58.089022",
      "check_type": "email_alert",
      "status": "no_emergency",
      "details": {
        "email_connection": "indirect_check",
        "alert_keywords": [
          "AI\u8d22\u5e93",
          "AINN",
          "HDAO",
          "Centrifuge",
          "Ondo",
          "SingularityNET",
          "\u6280\u672f\u56e2\u961f",
          "\u4f1a\u8bae\u65f6\u95f4",
          "\u5c3d\u804c\u8c03\u67e5",
          "\u6295\u8d44\u610f\u5411",
          "L-150",
          "RWA",
          "treasury",
          "investment",
          "meeting",
          "due diligence"
        ],
        "sender_keywords": [
          "ainn.xyz",
          "humanitydao.io",
          "centrifuge.io",
          "ondo.finance",
          "singularitynet.io"
        ]
      }
    },
    {
      "timestamp": "2026-02-18T05:34:00.649511",
      "check_type": "email_alert",
      "status": "no_emergency",
      "details": {
        "email_connection": "indirect_check",
        "alert_keywords": [
          "AI\u8d22\u5e93",
          "AINN",
          "HDAO",
          "Centrifuge",
          "Ondo",
          "SingularityNET",
          "\u6280\u672f\u56e2\u961f",
          "\u4f1a\u8bae\u65f6\u95f4",
          "\u5c3d\u804c\u8c03\u67e5",
          "\u6295\u8d44\u610f\u5411",
          "L-150",
          "RWA",
          "treasury",
          "investment",
          "meeting",
          "due diligence"
        ],
        "sender_keywords": [
          "ainn.xyz",
          "humanitydao.io",
          "centrifuge.io",
          "ondo.finance",
          "singularitynet.io"
        ]
      }
    },
    {
      "timestamp": "2026-02-18T05:44:42.998953",
      "check_type": "email_alert",
      "status": "no_emergency",
      "details": {
        "email_connection": "indirect_check",
        "alert_keywords": [
          "AI\u8d22\u5e93",
          "AINN",
          "HDAO",
          "Centrifuge",
          "Ondo",
          "SingularityNET",
          "\u6280\u672f\u56e2\u961f",
          "\u4f1a\u8bae\u65f6\u95f4",
          "\u5c3d\u804c\u8c03\u67e5",
          "\u6295\u8d44\u610f\u5411",
          "L-150",
          "RWA",
          "treasury",
          "investment",
          "meeting",
          "due diligence"
        ],
        "sender_keywords": [
          "ainn.xyz",
          "humanitydao.io",
          "centrifuge.io",
          "ondo.finance",
          "singularitynet.io"
        ]
      }
    },
    {
      "timestamp": "2026-02-18T05:48:55.814701",
      "check_type": "email_alert",
      "status": "no_emergency",
      "details": {
        "email_connection": "indirect_check",
        "alert_keywords": [
          "AI\u8d22\u5e93",
          "AINN",
          "HDAO",
          "Centrifuge",
          "Ondo",
          "SingularityNET",
          "\u6280\u672f\u56e2\u961f",
          "\u4f1a\u8bae\u65f6\u95f4",
          "\u5c3d\u804c\u8c03\u67e5",
          "\u6295\u8d44\u610f\u5411",
          "L-150",
          "RWA",
          "treasury",
          "investment",
          "meeting",
          "due diligence"
        ],
        "sender_keywords": [
          "ainn.xyz",
          "humanitydao.io",
          "centrifuge.io",
          "ondo.finance",
          "singularitynet.io"
        ]
      }
    },
    {
      "timestamp": "2026-02-18T05:58:51.168656",
      "check_type": "email_alert",
      "status": "no_emergency",
      "details": {
        "email_connection": "indirect_check",
        "alert_keywords": [
          "AI\u8d22\u5e93",
          "AINN",
          "HDAO",
          "Centrifuge",
          "Ondo",
          "SingularityNET",
          "\u6280\u672f\u56e2\u961f",
          "\u4f1a\u8bae\u65f6\u95f4",
          "\u5c3d\u804c\u8c03\u67e5",
          "\u6295\u8d44\u610f\u5411",
          "L-150",
          "RWA",
          "treasury",
          "investment",
          "meeting",
          "due diligence"
        ],
        "sender_keywords": [
          "ainn.xyz",
          "humanitydao.io",
          "centrifuge.io",
          "ondo.finance",
          "singularitynet.io"
        ]
      }
    },
    {
      "timestamp": "2026-02-18T06:03:50.502614",
      "check_type": "email_alert",
      "status": "no_emergency",
      "details": {
        "email_connection": "indirect_check",
        "alert_keywords": [
          "AI\u8d22\u5e93",
          "AINN",
          "HDAO",
          "Centrifuge",
          "Ondo",
          "SingularityNET",
          "\u6280\u672f\u56e2\u961f",
          "\u4f1a\u8bae\u65f6\u95f4",
          "\u5c3d\u804c\u8c03\u67e5",
          "\u6295\u8d44\u610f\u5411",
          "L-150",
          "RWA",
          "treasury",
          "investment",
          "meeting",
          "due diligence"
        ],
        "sender_keywords": [
          "ainn.xyz",
          "humanitydao.io",
          "centrifuge.io",
          "ondo.finance",
          "singularitynet.io"
        ]
      }
    },
    {
      "timestamp": "2026-02-18T06:23:53.242979",
      "check_type": "email_alert",
      "status": "no_emergency",
      "details": {
        "email_connection": "indirect_check",
        "alert_keywords": [
          "AI\u8d22\u5e93",
          "AINN",
          "HDAO",
          "Centrifuge",
          "Ondo",
          "SingularityNET",
          "\u6280\u672f\u56e2\u961f",
          "\u4f1a\u8bae\u65f6\u95f4",
          "\u5c3d\u804c\u8c03\u67e5",
          "\u6295\u8d44\u610f\u5411",
          "L-150",
          "RWA",
          "treasury",
          "investment",
          "meeting",
          "due diligence"
        ],
        "sender_keywords": [
          "ainn.xyz",
          "humanitydao.io",
          "centrifuge.io",
          "ondo.finance",
          "singularitynet.io"
        ]
      }
    },
    {
      "timestamp": "2026-02-18T06:59:00.986582",
      "check_type": "email_alert",
      "status": "no_emergency",
      "details": {
        "email_connection": "indirect_check",
        "alert_keywords": [
          "AI\u8d22\u5e93",
          "AINN",
          "HDAO",
          "Centrifuge",
          "Ondo",
          "SingularityNET",
          "\u6280\u672f\u56e2\u961f",
          "\u4f1a\u8bae\u65f6\u95f4",
          "\u5c3d\u804c\u8c03\u67e5",
          "\u6295\u8d44\u610f\u5411",
          "L-150",
          "RWA",
          "treasury",
          "investment",
          "meeting",
          "due diligence"
        ],
        "sender_keywords": [
          "ainn.xyz",
          "humanitydao.io",
          "centrifuge.io",
          "ondo.finance",
          "singularitynet.io"
        ]
      }
    },
    {
      "timestamp": "2026-02-18T07:04:30.914657",
      "check_type": "email_alert",
      "status": "no_emergency",
      "details": {
        "email_connection": "indirect_check",
        "alert_keywords": [
          "AI\u8d22\u5e93",
          "AINN",
          "HDAO",
          "Centrifuge",
          "Ondo",
          "SingularityNET",
          "\u6280\u672f\u56e2\u961f",
          "\u4f1a\u8bae\u65f6\u95f4",
          "\u5c3d\u804c\u8c03\u67e5",
          "\u6295\u8d44\u610f\u5411",
          "L-150",
          "RWA",
          "treasury",
          "investment",
          "meeting",
          "due diligence"
        ],
        "sender_keywords": [
          "ainn.xyz",
          "humanitydao.io",
          "centrifuge.io",
          "ondo.finance",
          "singularitynet.io"
        ]
      }
    },
    {
      "timestamp": "2026-02-18T07:24:34.201589",
      "check_type": "email_alert",
      "status": "no_emergency",
      "details": {
        "email_connection": "indirect_check",
        "alert_keywords": [
          "AI\u8d22\u5e93",
          "AINN",
          "HDAO",
          "Centrifuge",
          "Ondo",
          "SingularityNET",
          "\u6280\u672f\u56e2\u961f",
          "\u4f1a\u8bae\u65f6\u95f4",
          "\u5c3d\u804c\u8c03\u67e5",
          "\u6295\u8d44\u610f\u5411",
          "L-150",
          "RWA",
          "treasury",
          "investment",
          "meeting",
          "due diligence"
        ],
        "sender_keywords": [
          "ainn.xyz",
          "humanitydao.io",
          "centrifuge.io",
          "ondo.finance",
          "singularitynet.io"
        ]
      }
    },
    {
      "timestamp": "2026-02-18T07:33:58.549262",
      "check_type": "email_alert",
      "status": "no_emergency",
      "details": {
        "email_connection": "indirect_check",
        "alert_keywords": [
          "AI\u8d22\u5e93",
          "AINN",
          "HDAO",
          "Centrifuge",
          "Ondo",
          "SingularityNET",
          "\u6280\u672f\u56e2\u961f",
          "\u4f1a\u8bae\u65f6\u95f4",
          "\u5c3d\u804c\u8c03\u67e5",
          "\u6295\u8d44\u610f\u5411",
          "L-150",
          "RWA",
          "treasury",
          "investment",
          "meeting",
          "due diligence"
        ],
        "sender_keywords": [
          "ainn.xyz",
          "humanitydao.io",
          "centrifuge.io",
          "ondo.finance",
          "singularitynet.io"
        ]
      }
    },
    {
      "timestamp": "2026-02-18T07:34:05.000000",
      "check_type": "emergency_response",
      "status": "no_emergency",
      "details": {
        "gateway_status": "running",
        "github_activity": "zero_external_attention",
        "api_status": "github_pages_200_vercel_404",
        "cron_status": "1_error_9_normal",
        "email_outreach": "106_hours_no_reply",
        "technical_issues": [
          "vercel_api_404",
          "email_monitor_needs_fix",
          "cron_task_error"
        ]
      }
    },
    {
      "timestamp": "2026-02-18T07:49:17.731877",
      "check_type": "email_alert",
      "status": "no_emergency",
      "details": {
        "email_connection": "indirect_check",
        "alert_keywords": [
          "AI\u8d22\u5e93",
          "AINN",
          "HDAO",
          "Centrifuge",
          "Ondo",
          "SingularityNET",
          "\u6280\u672f\u56e2\u961f",
          "\u4f1a\u8bae\u65f6\u95f4",
          "\u5c3d\u804c\u8c03\u67e5",
          "\u6295\u8d44\u610f\u5411",
          "L-150",
          "RWA",
          "treasury",
          "investment",
          "meeting",
          "due diligence"
        ],
        "sender_keywords": [
          "ainn.xyz",
          "humanitydao.io",
          "centrifuge.io",
          "ondo.finance",
          "singularitynet.io"
        ]
      }
    },
    {
      "timestamp": "2026-02-18T08:14:04.313823",
      "check_type": "email_alert",
      "status": "no_emergency",
      "details": {
        "email_connection": "indirect_check",
        "alert_keywords": [
          "AI\u8d22\u5e93",
          "AINN",
          "HDAO",
          "Centrifuge",
          "Ondo",
          "SingularityNET",
          "\u6280\u672f\u56e2\u961f",
          "\u4f1a\u8bae\u65f6\u95f4",
          "\u5c3d\u804c\u8c03\u67e5",
          "\u6295\u8d44\u610f\u5411",
          "L-150",
          "RWA",
          "treasury",
          "investment",
          "meeting",
          "due diligence"
        ],
        "sender_keywords": [
          "ainn.xyz",
          "humanitydao.io",
          "centrifuge.io",
          "ondo.finance",
          "singularitynet.io"
        ]
      }
    }
  ],
  "last_check": "2026-02-18T08:14:04.313838"
}